nicebook/__init__.py
nicebook/cli.py
nicebook/configs.py
nicebook/generator.py
nicebook/nicebook_doc_template.py
nicebook/reference_manager.py
nicebook/styler.py
nicebook/utils.py
nicebook/components/__init__.py
nicebook/components/better_image.py
nicebook/components/checkbox.py
nicebook/components/list.py
nicebook/components/rich_paragraph.py
tests/__init__.py
tests/test_pdf_generation.py
nicebook-0.1.3.dist-info/LICENSE
nicebook-0.1.3.dist-info/METADATA
nicebook-0.1.3.dist-info/WHEEL
nicebook-0.1.3.dist-info/entry_points.txt
nicebook-0.1.3.dist-info/top_level.txt
nicebook-0.1.3.dist-info/RECORD
